pyspk/__init__.py
pyspk/fit_vals.py
pyspk/model.py
pyspk/stat_errors_200.csv
pyspk/stat_errors_500.csv
pyspk/__pycache__/__init__.cpython-38.pyc
pyspk/__pycache__/fit_vals.cpython-38.pyc
pyspk/__pycache__/model.cpython-38.pyc
pyspk-1.8.dist-info/LICENSE.md
pyspk-1.8.dist-info/METADATA
pyspk-1.8.dist-info/WHEEL
pyspk-1.8.dist-info/top_level.txt
pyspk-1.8.dist-info/RECORD
