Metadata-Version: 2.1
Name: pyspk
Version: 1.8
Summary: Python package to predict the suppression of the total matter power spectrum due to baryonic physics
Home-page: https://github.com/jemme07/pyspk
Author: Jaime Salcido
Author-email: j.salcidonegrete@ljmu.ac.uk
Classifier: Programming Language :: Python :: 3
Classifier: License :: OSI Approved :: GNU Lesser General Public License v3 or later (LGPLv3+)
Classifier: Operating System :: OS Independent
License-File: LICENSE.md
Requires-Dist: numpy
Requires-Dist: scipy
